tests
tlr
