Metadata-Version: 2.1
Name: tlr
Version: 2.1.0
Summary: VOGAMOS (Volcanic Gas Monitoring System) data acquisition service library
Home-page: https://gitlab.com/bpptkg/tlr
Author: Indra Rudianto
Author-email: indrarudianto.official@gmail.com
License: MIT
Platform: UNKNOWN
Classifier: Development Status :: 5 - Production/Stable
Classifier: Environment :: Console
Classifier: Operating System :: POSIX :: Linux
Classifier: Intended Audience :: Science/Research
Classifier: Natural Language :: English
Classifier: Programming Language :: Python :: 3.6
Classifier: Programming Language :: Python :: 3.7
Classifier: Programming Language :: Python :: 3.8
Requires-Python: >=3.6
